{
  "feature_id": "003-impl-rereview-classify",
  "phase": "impl",
  "current_round": 1,
  "status": "has_open_high",
  "max_finding_id": 4,
  "findings": [
    {
      "id": "R1-F01",
      "origin_round": 1,
      "latest_round": 1,
      "severity": "high",
      "category": "forbidden_files",
      "file": "template/.specflow/review_impl_rereview_prompt.txt",
      "title": "Diff modifies a forbidden .specflow path",
      "detail": "The diff adds a new file under `.specflow/`. Per the review contract, implementation diffs must not touch `.specflow/` or `.specify/`. Move this asset out of the forbidden path or change the approved delivery mechanism before merging.",
      "status": "new",
      "relation": "new",
      "supersedes": null,
      "notes": ""
    },
    {
      "id": "R1-F02",
      "origin_round": 1,
      "latest_round": 1,
      "severity": "high",
      "category": "correctness",
      "file": "global/specflow.fix.md",
      "title": "Derived max_finding_id is not persisted on write",
      "detail": "Branch E derives MAX_FINDING_ID from existing findings when the ledger lacks max_finding_id, but the write path later computes new_max = max(prev_ledger.max_finding_id || 0, max(new_findings...)). If a legacy ledger is missing max_finding_id and the re-review finds no new issues, the saved ledger regresses to 0 instead of the derived max.",
      "status": "new",
      "relation": "new",
      "supersedes": null,
      "notes": ""
    },
    {
      "id": "R1-F03",
      "origin_round": 1,
      "latest_round": 1,
      "severity": "high",
      "category": "correctness",
      "file": "global/specflow.fix.md",
      "title": "Decision is not recomputed after prior-ID validation",
      "detail": "The re-review flow auto-corrects Codex output by adding missing prior IDs to still_open_previous_findings and preferring still_open on duplicates, but it never recalculates decision after those corrections.",
      "status": "new",
      "relation": "new",
      "supersedes": null,
      "notes": ""
    },
    {
      "id": "R1-F04",
      "origin_round": 1,
      "latest_round": 1,
      "severity": "medium",
      "category": "testing",
      "file": "global/specflow.fix.md",
      "title": "No coverage for the new re-review branches and ledger edge cases",
      "detail": "This change adds non-trivial behavior across prompt switching, corrupt-ledger handling, prior-ID validation, and max_finding_id persistence, but the diff includes no tests or reproducible verification artifacts.",
      "status": "new",
      "relation": "new",
      "supersedes": null,
      "notes": ""
    }
  ],
  "round_summaries": [
    {
      "round": 1,
      "total": 4,
      "open": 0,
      "new": 4,
      "resolved": 0,
      "overridden": 0,
      "by_severity": {
        "high": { "open": 0, "resolved": 0, "new": 3, "overridden": 0 },
        "medium": { "open": 0, "resolved": 0, "new": 1, "overridden": 0 },
        "low": { "open": 0, "resolved": 0, "new": 0, "overridden": 0 }
      }
    }
  ]
}
